LICENSE
MANIFEST.in
README.rst
setup.cfg
setup.py
pipapp/__init__.py
pipapp/__main__.py
pipapp/pipapp.py
pipapp/texts.py
pipapp.egg-info/PKG-INFO
pipapp.egg-info/SOURCES.txt
pipapp.egg-info/dependency_links.txt
pipapp.egg-info/entry_points.txt
pipapp.egg-info/top_level.txt