Metadata-Version: 1.1
Name: pipapp
Version: 0.2
Summary: Create basic files and directories for pip-dist enabled Python apps.
Home-page: https://github.com/samisalkosuo/pipapp
Author: Sami Salkosuo
Author-email: dev@rnd-dev.com
License: MIT
Platform: UNKNOWN
Classifier: Development Status :: 3 - Alpha
Classifier: Intended Audience :: Developers
Classifier: Environment :: Console
Classifier: License :: OSI Approved :: MIT License
Classifier: Natural Language :: English
Classifier: Operating System :: OS Independent
Classifier: Programming Language :: Python :: 3
Classifier: Topic :: Software Development
Classifier: Topic :: Utilities
